ch/__init__.py
ch/sachi/__init__.py
ch/sachi/weatherstation/__init__.py
ch/sachi/weatherstation/config.py
ch/sachi/weatherstation/domain.py
ch/sachi/weatherstation/logging.py
ch/sachi/weatherstation/measureRepository.py
ch/sachi/weatherstation/publishMeasures.py
ch/sachi/weatherstation/publishPictures.py
ch/sachi/weatherstation/restServiceMeasures.py
ch/sachi/weatherstation/restServicePictures.py
ch/sachi/weatherstation/saveMeasures.py
ch/sachi/weatherstation/tf/__init__.py
ch/sachi/weatherstation/tf/deviceService.py
ch_sachi_weatherstation-3.3.0.dist-info/LICENSE
ch_sachi_weatherstation-3.3.0.dist-info/METADATA
ch_sachi_weatherstation-3.3.0.dist-info/WHEEL
ch_sachi_weatherstation-3.3.0.dist-info/entry_points.txt
ch_sachi_weatherstation-3.3.0.dist-info/RECORD
