Metadata-Version: 2.1
Name: ch.sachi.weatherstation
Version: 3.3.0
Summary: Collects data from tinkerforge outdoor weather station and saves it to sqlite database.
Author: Patrick Zbinden
Author-email: patrick+dev@zbinden-online.ch
Requires-Python: >=3.9,<4.0
Classifier: Programming Language :: Python :: 3
Classifier: Programming Language :: Python :: 3.9
Classifier: Programming Language :: Python :: 3.10
Classifier: Programming Language :: Python :: 3.11
Requires-Dist: importlib-metadata (>=8.5.0,<9.0.0)
Requires-Dist: requests (==2.32.3)
Requires-Dist: tinkerforge (==2.1.31)
